subradar/Classdef.py
subradar/__init__.py
subradar/filtering.py
subradar/fractal.py
subradar/iem.py
subradar/invert.py
subradar/roughness.py
subradar/surface.py
subradar/utils.py
subradar/simulation/__init__.py
subradar/simulation/trento.py
subradar-1.1.5.dist-info/METADATA
subradar-1.1.5.dist-info/WHEEL
subradar-1.1.5.dist-info/top_level.txt
subradar-1.1.5.dist-info/RECORD
